dijkstra_conda/__init__.py
dijkstra_conda/cli.py
dijkstra_conda/ig_path.py
dijkstra_conda/ig_path_test.py
dijkstra_conda-98243576.dist-info/LICENSE
dijkstra_conda-98243576.dist-info/METADATA
dijkstra_conda-98243576.dist-info/WHEEL
dijkstra_conda-98243576.dist-info/entry_points.txt
dijkstra_conda-98243576.dist-info/top_level.txt
dijkstra_conda-98243576.dist-info/RECORD
