Metadata-Version: 2.1
Name: dijkstra_conda
Version: 98243576
Summary: A test project
Home-page: https://github.com/iHeadWater/dijkstra-conda
Author: dijkstra_conda-test
License: MIT
Keywords: dijkstra_conda
Classifier: Development Status :: 2 - Pre-Alpha
Classifier: Intended Audience :: Developers
Classifier: License :: OSI Approved :: MIT License
Classifier: Natural Language :: English
Classifier: Programming Language :: Python :: 3.6
Classifier: Programming Language :: Python :: 3.7
Classifier: Programming Language :: Python :: 3.8
Classifier: Programming Language :: Python :: 3.9
Classifier: Programming Language :: Python :: 3.10
Classifier: Programming Language :: Python :: 3.11
Classifier: Programming Language :: Python :: 3.12
Classifier: Programming Language :: Python :: Implementation :: CPython
Classifier: Programming Language :: Python :: Implementation :: PyPy
License-File: LICENSE
Requires-Dist: geopandas >=0.12.2
Requires-Dist: pytest >=7.1.3
Requires-Dist: setuptools >=63.4.1
Requires-Dist: click >=8.1.3
Requires-Dist: pandas >=1.4.3
Requires-Dist: shapely >=2.0.1
Requires-Dist: pyogrio >=0.4.2
Requires-Dist: igraph >=0.10.4
